{".class": "MypyFile", "_fullname": "networkx.algorithms.centrality", "is_partial_stub_package": false, "is_stub": false, "names": {".class": "SymbolTable", "__doc__": {".class": "SymbolTableNode", "kind": "Gdef", "node": {".class": "Var", "flags": ["is_ready"], "fullname": "networkx.algorithms.centrality.__doc__", "name": "__doc__", "type": "builtins.str"}}, "__file__": {".class": "SymbolTableNode", "kind": "Gdef", "node": {".class": "Var", "flags": ["is_ready"], "fullname": "networkx.algorithms.centrality.__file__", "name": "__file__", "type": "builtins.str"}}, "__name__": {".class": "SymbolTableNode", "kind": "Gdef", "node": {".class": "Var", "flags": ["is_ready"], "fullname": "networkx.algorithms.centrality.__name__", "name": "__name__", "type": "builtins.str"}}, "__package__": {".class": "SymbolTableNode", "kind": "Gdef", "node": {".class": "Var", "flags": ["is_ready"], "fullname": "networkx.algorithms.centrality.__package__", "name": "__package__", "type": "builtins.str"}}, "approximate_current_flow_betweenness_centrality": {".class": "SymbolTableNode", "cross_ref": "networkx.algorithms.centrality.current_flow_betweenness.approximate_current_flow_betweenness_centrality", "kind": "Gdef"}, "betweenness_centrality": {".class": "SymbolTableNode", "cross_ref": "networkx.algorithms.centrality.betweenness.betweenness_centrality", "kind": "Gdef"}, "betweenness_centrality_source": {".class": "SymbolTableNode", "cross_ref": "networkx.algorithms.centrality.betweenness_subset.betweenness_centrality_source", "kind": "Gdef"}, "betweenness_centrality_subset": {".class": "SymbolTableNode", "cross_ref": "networkx.algorithms.centrality.betweenness_subset.betweenness_centrality_subset", "kind": "Gdef"}, "closeness_centrality": {".class": "SymbolTableNode", "cross_ref": "networkx.algorithms.centrality.closeness.closeness_centrality", "kind": "Gdef"}, "communicability_betweenness_centrality": {".class": "SymbolTableNode", "cross_ref": "networkx.algorithms.centrality.subgraph_alg.communicability_betweenness_centrality", "kind": "Gdef"}, "current_flow_betweenness_centrality": {".class": "SymbolTableNode", "cross_ref": "networkx.algorithms.centrality.current_flow_betweenness.current_flow_betweenness_centrality", "kind": "Gdef"}, "current_flow_betweenness_centrality_subset": {".class": "SymbolTableNode", "cross_ref": "networkx.algorithms.centrality.current_flow_betweenness_subset.current_flow_betweenness_centrality_subset", "kind": "Gdef"}, "current_flow_closeness_centrality": {".class": "SymbolTableNode", "cross_ref": "networkx.algorithms.centrality.current_flow_closeness.current_flow_closeness_centrality", "kind": "Gdef"}, "degree_centrality": {".class": "SymbolTableNode", "cross_ref": "networkx.algorithms.centrality.degree_alg.degree_centrality", "kind": "Gdef"}, "dispersion": {".class": "SymbolTableNode", "cross_ref": "networkx.algorithms.centrality.dispersion.dispersion", "kind": "Gdef"}, "edge_betweenness": {".class": "SymbolTableNode", "cross_ref": "networkx.algorithms.centrality.betweenness.edge_betweenness", "kind": "Gdef"}, "edge_betweenness_centrality": {".class": "SymbolTableNode", "cross_ref": "networkx.algorithms.centrality.betweenness.edge_betweenness_centrality", "kind": "Gdef"}, "edge_betweenness_centrality_subset": {".class": "SymbolTableNode", "cross_ref": "networkx.algorithms.centrality.betweenness_subset.edge_betweenness_centrality_subset", "kind": "Gdef"}, "edge_current_flow_betweenness_centrality": {".class": "SymbolTableNode", "cross_ref": "networkx.algorithms.centrality.current_flow_betweenness.edge_current_flow_betweenness_centrality", "kind": "Gdef"}, "edge_current_flow_betweenness_centrality_subset": {".class": "SymbolTableNode", "cross_ref": "networkx.algorithms.centrality.current_flow_betweenness_subset.edge_current_flow_betweenness_centrality_subset", "kind": "Gdef"}, "edge_load_centrality": {".class": "SymbolTableNode", "cross_ref": "networkx.algorithms.centrality.load.edge_load_centrality", "kind": "Gdef"}, "eigenvector_centrality": {".class": "SymbolTableNode", "cross_ref": "networkx.algorithms.centrality.eigenvector.eigenvector_centrality", "kind": "Gdef"}, "eigenvector_centrality_numpy": {".class": "SymbolTableNode", "cross_ref": "networkx.algorithms.centrality.eigenvector.eigenvector_centrality_numpy", "kind": "Gdef"}, "estrada_index": {".class": "SymbolTableNode", "cross_ref": "networkx.algorithms.centrality.subgraph_alg.estrada_index", "kind": "Gdef"}, "global_reaching_centrality": {".class": "SymbolTableNode", "cross_ref": "networkx.algorithms.centrality.reaching.global_reaching_centrality", "kind": "Gdef"}, "harmonic_centrality": {".class": "SymbolTableNode", "cross_ref": "networkx.algorithms.centrality.harmonic.harmonic_centrality", "kind": "Gdef"}, "in_degree_centrality": {".class": "SymbolTableNode", "cross_ref": "networkx.algorithms.centrality.degree_alg.in_degree_centrality", "kind": "Gdef"}, "information_centrality": {".class": "SymbolTableNode", "cross_ref": "networkx.algorithms.centrality.current_flow_closeness.information_centrality", "kind": "Gdef"}, "katz_centrality": {".class": "SymbolTableNode", "cross_ref": "networkx.algorithms.centrality.katz.katz_centrality", "kind": "Gdef"}, "katz_centrality_numpy": {".class": "SymbolTableNode", "cross_ref": "networkx.algorithms.centrality.katz.katz_centrality_numpy", "kind": "Gdef"}, "load_centrality": {".class": "SymbolTableNode", "cross_ref": "networkx.algorithms.centrality.load.load_centrality", "kind": "Gdef"}, "local_reaching_centrality": {".class": "SymbolTableNode", "cross_ref": "networkx.algorithms.centrality.reaching.local_reaching_centrality", "kind": "Gdef"}, "out_degree_centrality": {".class": "SymbolTableNode", "cross_ref": "networkx.algorithms.centrality.degree_alg.out_degree_centrality", "kind": "Gdef"}, "percolation_centrality": {".class": "SymbolTableNode", "cross_ref": "networkx.algorithms.centrality.percolation.percolation_centrality", "kind": "Gdef"}, "second_order_centrality": {".class": "SymbolTableNode", "cross_ref": "networkx.algorithms.centrality.second_order.second_order_centrality", "kind": "Gdef"}, "subgraph_centrality": {".class": "SymbolTableNode", "cross_ref": "networkx.algorithms.centrality.subgraph_alg.subgraph_centrality", "kind": "Gdef"}, "subgraph_centrality_exp": {".class": "SymbolTableNode", "cross_ref": "networkx.algorithms.centrality.subgraph_alg.subgraph_centrality_exp", "kind": "Gdef"}, "voterank": {".class": "SymbolTableNode", "cross_ref": "networkx.algorithms.centrality.voterank_alg.voterank", "kind": "Gdef"}}, "path": "/home/fmagin/.virtualenvs/angr/lib/python3.7/site-packages/networkx/algorithms/centrality/__init__.py"}