{".class": "MypyFile", "_fullname": "networkx.algorithms.centrality.load", "is_partial_stub_package": false, "is_stub": false, "names": {".class": "SymbolTable", "__all__": {".class": "SymbolTableNode", "kind": "Gdef", "module_public": false, "node": {".class": "Var", "flags": [], "fullname": "networkx.algorithms.centrality.load.__all__", "name": "__all__", "type": null}}, "__doc__": {".class": "SymbolTableNode", "kind": "Gdef", "module_public": false, "node": {".class": "Var", "flags": ["is_ready"], "fullname": "networkx.algorithms.centrality.load.__doc__", "name": "__doc__", "type": "builtins.str"}}, "__file__": {".class": "SymbolTableNode", "kind": "Gdef", "module_public": false, "node": {".class": "Var", "flags": ["is_ready"], "fullname": "networkx.algorithms.centrality.load.__file__", "name": "__file__", "type": "builtins.str"}}, "__name__": {".class": "SymbolTableNode", "kind": "Gdef", "module_public": false, "node": {".class": "Var", "flags": ["is_ready"], "fullname": "networkx.algorithms.centrality.load.__name__", "name": "__name__", "type": "builtins.str"}}, "__package__": {".class": "SymbolTableNode", "kind": "Gdef", "module_public": false, "node": {".class": "Var", "flags": ["is_ready"], "fullname": "networkx.algorithms.centrality.load.__package__", "name": "__package__", "type": "builtins.str"}}, "_edge_betweenness": {".class": "SymbolTableNode", "kind": "Gdef", "module_public": false, "node": {".class": "FuncDef", "arg_kinds": [0, 0, 1, 1], "arg_names": ["G", "source", "nodes", "cutoff"], "flags": [], "fullname": "networkx.algorithms.centrality.load._edge_betweenness", "name": "_edge_betweenness", "type": null}}, "_node_betweenness": {".class": "SymbolTableNode", "kind": "Gdef", "module_public": false, "node": {".class": "FuncDef", "arg_kinds": [0, 0, 1, 1, 1], "arg_names": ["G", "source", "cutoff", "normalized", "weight"], "flags": [], "fullname": "networkx.algorithms.centrality.load._node_betweenness", "name": "_node_betweenness", "type": null}}, "division": {".class": "SymbolTableNode", "cross_ref": "__future__.division", "kind": "Gdef", "module_public": false}, "edge_load_centrality": {".class": "SymbolTableNode", "kind": "Gdef", "node": {".class": "FuncDef", "arg_kinds": [0, 1], "arg_names": ["G", "cutoff"], "flags": [], "fullname": "networkx.algorithms.centrality.load.edge_load_centrality", "name": "edge_load_centrality", "type": null}}, "itemgetter": {".class": "SymbolTableNode", "cross_ref": "operator.itemgetter", "kind": "Gdef", "module_public": false}, "load_centrality": {".class": "SymbolTableNode", "kind": "Gdef", "node": {".class": "Var", "flags": [], "fullname": "networkx.algorithms.centrality.load.load_centrality", "name": "load_centrality", "type": null}}, "newman_betweenness_centrality": {".class": "SymbolTableNode", "kind": "Gdef", "module_public": false, "node": {".class": "FuncDef", "arg_kinds": [0, 1, 1, 1, 1], "arg_names": ["G", "v", "cutoff", "normalized", "weight"], "flags": [], "fullname": "networkx.algorithms.centrality.load.newman_betweenness_centrality", "name": "newman_betweenness_centrality", "type": null}}, "nx": {".class": "SymbolTableNode", "cross_ref": "networkx", "kind": "Gdef", "module_public": false}}, "path": "/home/fmagin/.virtualenvs/angr/lib/python3.7/site-packages/networkx/algorithms/centrality/load.py"}