{"child_modules": ["networkx.algorithms.bipartite.projection", "networkx.algorithms.bipartite.edgelist", "networkx.algorithms.bipartite.spectral", "networkx.algorithms.bipartite.basic", "networkx.algorithms.bipartite.covering", "networkx.algorithms.bipartite.matching", "networkx.algorithms.bipartite.cluster", "networkx.algorithms.bipartite.generators", "networkx.algorithms.bipartite.matrix", "networkx.algorithms.bipartite.redundancy", "networkx.algorithms.bipartite.centrality"], "data_mtime": 1567773663, "dep_lines": [77, 78, 79, 80, 81, 82, 83, 84, 85, 86, 87, 1, 1, 1, 1, 1, 1, 1, 1, 1], "dep_prios": [5, 5, 5, 5, 5, 5, 5, 5, 5, 5, 5, 5, 20, 20, 20, 20, 20, 20, 20, 20], "dependencies": ["networkx.algorithms.bipartite.basic", "networkx.algorithms.bipartite.centrality", "networkx.algorithms.bipartite.cluster", "networkx.algorithms.bipartite.covering", "networkx.algorithms.bipartite.edgelist", "networkx.algorithms.bipartite.matching", "networkx.algorithms.bipartite.matrix", "networkx.algorithms.bipartite.projection", "networkx.algorithms.bipartite.redundancy", "networkx.algorithms.bipartite.spectral", "networkx.algorithms.bipartite.generators", "builtins", "uuid", "sys", "warnings", "pyexpat.model", "networkx", "operator", "pyexpat.errors", "random"], "hash": "516352d30ad1ca14dcf5b294e13dab9f", "id": "networkx.algorithms.bipartite", "ignore_all": false, "interface_hash": "2fc279efb8dea3cda4603ec09f90d487", "mtime": 1567423200, "options": {"allow_redefinition": false, "allow_untyped_globals": false, "always_false": [], "always_true": [], "bazel": false, "check_untyped_defs": false, "disallow_any_decorated": false, "disallow_any_explicit": false, "disallow_any_expr": false, "disallow_any_generics": false, "disallow_any_unimported": false, "disallow_incomplete_defs": false, "disallow_subclassing_any": false, "disallow_untyped_calls": false, "disallow_untyped_decorators": false, "disallow_untyped_defs": false, "follow_imports": "skip", "follow_imports_for_stubs": false, "ignore_errors": true, "ignore_missing_imports": false, "implicit_reexport": true, "local_partial_types": false, "mypyc": false, "new_semantic_analyzer": true, "no_implicit_optional": false, "platform": "linux", "plugins": [], "show_none_errors": true, "strict_equality": false, "strict_optional": true, "strict_optional_whitelist": null, "warn_no_return": true, "warn_return_any": false, "warn_unreachable": false, "warn_unused_ignores": false}, "path": "/home/fmagin/.virtualenvs/angr/lib/python3.7/site-packages/networkx/algorithms/bipartite/__init__.py", "size": 3794, "suppressed": [], "version_id": "0.720"}